cli/__init__.py
cli/cli.py
cli/config.py
gpu_cluster_cli-0.4.8.dist-info/METADATA
gpu_cluster_cli-0.4.8.dist-info/WHEEL
gpu_cluster_cli-0.4.8.dist-info/entry_points.txt
gpu_cluster_cli-0.4.8.dist-info/top_level.txt
gpu_cluster_cli-0.4.8.dist-info/RECORD
