Metadata-Version: 2.1
Name: gpu-cluster-cli
Version: 0.4.8
Summary: GPU Cluster Command Line Interface
Home-page: UNKNOWN
Maintainer: LG CNS AI Research Team
Maintainer-email: jibm@lgcns.com
License: BSD
Platform: UNKNOWN
Requires-Dist: click (==7.0)
Requires-Dist: executor (==21.3)
Requires-Dist: requests (==2.20.1)
Requires-Dist: terminaltables (==3.1.0)
Requires-Dist: pyfiglet (==0.8.post0)
Provides-Extra: test
Requires-Dist: pytest (==3.10.1) ; extra == 'test'
Requires-Dist: coverage (==4.5.2) ; extra == 'test'
